autoclockify/__init__.py
autoclockify/__main__.py
autoclockify/ac.py
autoclockify/api_client.py
autoclockify/config.py
auto_clockify-0.0.6.dist-info/LICENSE.txt
auto_clockify-0.0.6.dist-info/METADATA
auto_clockify-0.0.6.dist-info/WHEEL
auto_clockify-0.0.6.dist-info/entry_points.txt
auto_clockify-0.0.6.dist-info/top_level.txt
auto_clockify-0.0.6.dist-info/RECORD
