Metadata-Version: 2.1
Name: auto-clockify
Version: 0.0.6
Summary: Automation code snipplets to start and stop Clockify via API calls.
Home-page: https://github.com/adamjakab/AutoClockify
Author: Adam Jakab
Author-email: adam@jakab.pro
License: MIT
Platform: ALL
Classifier: License :: OSI Approved :: MIT License
Classifier: Environment :: Console
Classifier: Programming Language :: Python :: 3
Requires-Python: >=3.6
Requires-Dist: requests
Provides-Extra: tests
